MANIFEST.in
README.md
setup.py
rainfall/__init__.py
rainfall/http.py
rainfall/unittest.py
rainfall/utils.py
rainfall/web.py
rainfall.egg-info/PKG-INFO
rainfall.egg-info/SOURCES.txt
rainfall.egg-info/dependency_links.txt
rainfall.egg-info/requires.txt
rainfall.egg-info/top_level.txt