Metadata-Version: 1.1
Name: rainfall
Version: 0.8.3
Summary: Micro web framework around asyncio (ex tulip)
Home-page: https://github.com/mind1master/rainfall
Author: Anton Kasyanov
Author-email: antony.kasyanov@gmail.com
License: 
